setup.py
simplest/__init__.py
simplest/core.py
simplest.egg-info/PKG-INFO
simplest.egg-info/SOURCES.txt
simplest.egg-info/dependency_links.txt
simplest.egg-info/requires.txt
simplest.egg-info/top_level.txt