Metadata-Version: 1.0
Name: simplest
Version: 0.2
Summary: Working with Redis should be simple and Pythonic.
Home-page: http://github.com/zachwill/simplest
Author: Zach Williams
Author-email: hey@zachwill.com
License: MIT
Keywords: redis,simplest,zach will,simple
Platform: UNKNOWN
Classifier: Development Status :: 4 - Beta
Classifier: Environment :: Console
Classifier: Intended Audience :: Developers
Classifier: Intended Audience :: End Users/Desktop
Classifier: License :: OSI Approved :: MIT License
Classifier: Natural Language :: English
Classifier: Operating System :: OS Independent
Classifier: Programming Language :: Python
Classifier: Programming Language :: Python :: 2.6
Classifier: Programming Language :: Python :: 2.7
Classifier: Topic :: Scientific/Engineering :: Information Analysis
Classifier: Topic :: Software Development :: Libraries :: Python Modules
Classifier: Topic :: Utilities
